[
  {
    "job_id": "various_positions_the_uae_career_uae",
    "title": "Various Positions",
    "company": "The UAE Career",
    "location": "UAE",
    "link": "https://theuaejobs.com/job-openings/",
    "score": 0.5,
    "status": "interview_scheduled",
    "date_applied": "2026-05-03T17:56:14.424989",
    "date_updated": "2026-05-05T04:48:35.365248",
    "notes": "Auto-imported from Gmail: Your Application Status – Interview Round",
    "interview_date": null,
    "rejection_reason": null
  },
  {
    "title": "Environmental & Sustainability Manager",
    "company": "Parsons Corporation",
    "link": "https://ae.linkedin.com/jobs/view/environmental-sustainability-manager-at-parsons-corporation-4370574267",
    "status": "applied",
    "date_applied": "2026-05-04T05:11:38.237504",
    "notes": "Applied via Parsons portal"
  },
  {
    "title": "HSE Manager",
    "company": "Confidential Dubai",
    "link": "https://ae.linkedin.com/jobs/view/environment-health-and-safety-manager-at-confidential-4399872800",
    "status": "no_response",
    "date_applied": "2026-05-04T04:58:46.264848",
    "notes": "Applied via LinkedIn - EHS Manager Confidential Dubai",
    "date_updated": "2026-05-04T05:02:06.055650"
  },
  {
    "title": "ESG Manager",
    "company": "LOBA GROUP",
    "link": "https://ae.linkedin.com/jobs/view/esg-manager-at-loba-group-4400819814",
    "status": "no_response",
    "date_applied": "2026-05-04T04:58:46.264850",
    "notes": "Applied via LinkedIn - LOBA GROUP",
    "date_updated": "2026-05-04T05:01:34.191332"
  },
  {
    "title": "Sustainability Manager",
    "company": "KAYALI",
    "link": "https://ae.linkedin.com/jobs/view/sustainability-manager-at-kayali-4404967910",
    "status": "no_response",
    "date_applied": "2026-05-04T04:58:46.264851",
    "notes": "Applied via LinkedIn - Sustainability Manager KAYALI",
    "date_updated": "2026-05-04T05:02:09.716626"
  },
  {
    "title": "HSSE Manager-CCGT",
    "company": "Al Jomaih Energy and Water",
    "link": "https://ae.linkedin.com/jobs/view/hsse-manager-ccgt-at-aljomaih-energy-and-water-company-4399850554",
    "status": "no_response",
    "date_applied": "2026-05-04T05:11:38.237473",
    "notes": "Application received confirmation - under review",
    "date_updated": "2026-05-04T05:23:58.388790"
  },
  {
    "title": "Project HSE Manager",
    "company": "Talents Tide",
    "link": "https://ae.linkedin.com/jobs/view/project-hse-manager-at-talents-tide-4394408260",
    "status": "applied",
    "date_applied": "2026-05-04T05:11:38.237497",
    "notes": "Applied via LinkedIn"
  },
  {
    "title": "Environment, Health and Safety Manager",
    "company": "Aljomaih Energy and Water",
    "link": "https://ae.linkedin.com/jobs/view/environment-health-and-safety-manager-at-aljomaih-energy-and-water-4397838307",
    "status": "applied",
    "date_applied": "2026-05-04T05:11:38.237499",
    "notes": "Applied via LinkedIn"
  },
  {
    "title": "EHS Manager",
    "company": "Larsen & Toubro",
    "link": "https://ae.linkedin.com/jobs/view/ehs-manager-at-larsen-toubro-4397838307",
    "status": "applied",
    "date_applied": "2026-05-04T05:11:38.237500",
    "notes": "Applied via LinkedIn"
  },
  {
    "title": "Project HSE Manager",
    "company": "Penta Global Engineering",
    "link": "https://ae.linkedin.com/jobs/view/project-health-safety-environment-manager-at-penta-global-engineering-4396257804",
    "status": "applied",
    "date_applied": "2026-05-04T05:11:38.237501",
    "notes": "Applied via LinkedIn"
  },
  {
    "title": "EHS Manager",
    "company": "Confidential",
    "link": "https://ae.linkedin.com/jobs/view/ehs-manager-at-confidential-4399872800",
    "status": "applied",
    "date_applied": "2026-05-04T05:11:38.237503",
    "notes": "Applied via LinkedIn"
  },
  {
    "job_id": "whs_manager_uae_fc_amazon_uae",
    "title": "WHS Manager UAE FC",
    "company": "Amazon",
    "location": "UAE",
    "link": "https://ae.linkedin.com/jobs/view/whs-manager-uae-fc-at-amazon-4377846953",
    "score": 90,
    "status": "applied",
    "date_applied": "2026-05-04T05:56:52.301768",
    "date_updated": "2026-05-05T04:48:31.437116",
    "notes": "Auto-imported from Gmail: Thank you for Applying to Amazon!",
    "interview_date": null,
    "rejection_reason": null
  },
  {
    "job_id": "senior_associate_-_esg_compliance_ega_abu_dhabi,_az,_ae",
    "title": "Senior Associate - ESG Compliance",
    "company": "EGA",
    "location": "Abu Dhabi, AZ, AE",
    "link": "https://ae.indeed.com/viewjob?jk=d70e123078a78081",
    "score": 65,
    "status": "no_response",
    "date_applied": "2026-05-04T06:05:06.590589",
    "date_updated": "2026-05-04T06:12:53.093549",
    "notes": "EGA confirmed receipt - under preliminary screening",
    "interview_date": null,
    "rejection_reason": null
  }
]